yt_dl_cli/__init__.py
yt_dl_cli/main.py
yt_dl_cli/config/__init__.py
yt_dl_cli/config/config.py
yt_dl_cli/core/__init__.py
yt_dl_cli/core/core.py
yt_dl_cli/core/orchestration.py
yt_dl_cli/i18n/__init__.py
yt_dl_cli/i18n/init.py
yt_dl_cli/i18n/messages.py
yt_dl_cli/interfaces/__init__.py
yt_dl_cli/interfaces/interfaces.py
yt_dl_cli/interfaces/strategies.py
yt_dl_cli/locales/de/LC_MESSAGES/messages.mo
yt_dl_cli/locales/de/LC_MESSAGES/messages.po
yt_dl_cli/locales/en/LC_MESSAGES/messages.mo
yt_dl_cli/locales/en/LC_MESSAGES/messages.po
yt_dl_cli/locales/ru/LC_MESSAGES/messages.mo
yt_dl_cli/locales/ru/LC_MESSAGES/messages.po
yt_dl_cli/locales/uk/LC_MESSAGES/messages.mo
yt_dl_cli/locales/uk/LC_MESSAGES/messages.po
yt_dl_cli/scripts/__init__.py
yt_dl_cli/scripts/cli.py
yt_dl_cli/utils/__init__.py
yt_dl_cli/utils/logger.py
yt_dl_cli/utils/parser.py
yt_dl_cli/utils/stats_manager.py
yt_dl_cli/utils/utils.py
yt_dl_cli/utils/validators.py
yt_dl_cli-1.0.4.dist-info/licenses/LICENSE
yt_dl_cli-1.0.4.dist-info/METADATA
yt_dl_cli-1.0.4.dist-info/WHEEL
yt_dl_cli-1.0.4.dist-info/entry_points.txt
yt_dl_cli-1.0.4.dist-info/top_level.txt
yt_dl_cli-1.0.4.dist-info/RECORD
