Metadata-Version: 2.4
Name: yt_dl_cli
Version: 1.0.4
Summary: Video downloader from a number of video streaming services.
Author-email: Oleksandr Kharchenko <kharchenko.oleksandr@icloud.com>
License: MIT
Classifier: Programming Language :: Python :: 3
Classifier: License :: OSI Approved :: MIT License
Classifier: Operating System :: OS Independent
Requires-Python: >=3.8
License-File: LICENSE
Requires-Dist: yt-dlp>=2024.0.0
Dynamic: license-file
